prueba1_gha/__init__.py
prueba1_gha/main.py
prueba1_gha/operations.py
prueba1_gha/py.typed.py
prueba1_gha-0.2.0.dist-info/METADATA
prueba1_gha-0.2.0.dist-info/WHEEL
prueba1_gha-0.2.0.dist-info/RECORD
